mlargparser.py
mlargparser-0.8.dist-info/LICENSE
mlargparser-0.8.dist-info/METADATA
mlargparser-0.8.dist-info/WHEEL
mlargparser-0.8.dist-info/top_level.txt
mlargparser-0.8.dist-info/RECORD
