Metadata-Version: 2.1
Name: mlargparser
Version: 0.8
Summary: A multi-Level argument parser library for writing CLI-based applications
Author-email: Jared Sutton <jpsutton@gmail.com>
Project-URL: Homepage, https://github.com/jpsutton/mlargparser
Project-URL: Bug Tracker, https://github.com/jpsutton/mlargparser/issues
Classifier: Programming Language :: Python :: 3
Classifier: License :: OSI Approved :: GNU Lesser General Public License v2 (LGPLv2)
Classifier: Operating System :: OS Independent
Requires-Python: >=3.3
License-File: LICENSE
